VASPsol/GammaLoaders.py
VASPsol/NIST.py
VASPsol/VASPsol.py
VASPsol/__init__.py
VASPsol/custom.py
VASPsol/sigma_functions.py
VASPsol-0.1.5.dist-info/METADATA
VASPsol-0.1.5.dist-info/WHEEL
VASPsol-0.1.5.dist-info/top_level.txt
VASPsol-0.1.5.dist-info/RECORD
